citerate/__init__.py
citerate/citerate.py
citerate-0.1.1.dist-info/LICENSE
citerate-0.1.1.dist-info/METADATA
citerate-0.1.1.dist-info/WHEEL
citerate-0.1.1.dist-info/top_level.txt
citerate-0.1.1.dist-info/RECORD
